eyesim/__init__.py
eyesim/etc.py
eyesim/helpers.py
eyesim/runner.py
eyesim/test-mode/main.py
eyesim/test-mode/test.wav
eyesim-0.0.3.data/data/requirements.txt
eyesim-0.0.3.data/data/test-mode_main/main.py
eyesim-0.0.3.data/data/test-mode_wave/test.wav
eyesim-0.0.3.dist-info/LICENSE
eyesim-0.0.3.dist-info/METADATA
eyesim-0.0.3.dist-info/WHEEL
eyesim-0.0.3.dist-info/entry_points.txt
eyesim-0.0.3.dist-info/top_level.txt
eyesim-0.0.3.dist-info/RECORD
