Metadata-Version: 2.1
Name: eyesim
Version: 0.0.3
Summary: eyesy simulator
Home-page: https://github.com/notmatthancock/eyesim
Author: Matt Hancock
Author-email: not.matt.hancock@gmail.com
Classifier: License :: OSI Approved :: MIT License
Requires-Python: >=3.8
License-File: LICENSE
Requires-Dist: pygame (==2.1.2)
Requires-Dist: pygame-widgets (==1.0.0)
Requires-Dist: scipy (==1.8.1)
